[{"SetID":56863,"Number":30365,"Variant":1,"YearFrom":2019,"Category":"Normal","Theme":"Mars Exploration","ThemeGroup":"City","Subtheme":null,"SetName":"Space Satellite","Image":"X","ImageFilename":"30365-1","USRetailPrice":null,"UKRetailPrice":null,"CARetailPrice":null,"DERetailPrice":null,"USDateAdded":null,"USDateRemoved":null,"Pieces":36,"Minifigs":null,"MinifigNumbers":null,"PackagingType":null,"Availability":null,"USItemNumber":null,"EUItemNumber":null,"EAN":null,"UPC":null,"Width":null,"Height":null,"Depth":null,"Weight":null,"ModelDimension1":null,"ModelDimension2":null,"ModelDimension3":null,"AgeMin":null,"AgeMax":null,"OwnCount":null,"WantCount":null,"InstructionsCount":null,"AdditionalImageCount":null,"Released":null,"Rating":null,"BrickLinkSoldPriceNew":null,"BrickLinkSoldPriceUsed":null,"Designers":null,"LaunchDate":null,"ExitDate":null,"link":"https://www.bricklink.com/v2/catalog/catalogitem.page?S=30365-1#T=P","productImage":"https://cdn.rebrickable.com/media/sets/30365-1.jpg","instructionsLink":"","type":"Set","New":null,"Used":null,"ExclusiveMinifigNumbers":null,"ExclusiveMinifigCount":null,"CurrentRRPBaseline":null},{"SetID":58800,"Number":40345,"Variant":1,"YearFrom":2019,"Category":"Normal","Theme":"Mars Exploration","ThemeGroup":"City","Subtheme":null,"SetName":"Mars Exploration Minifigure Pack","Image":"X","ImageFilename":"40345-1","USRetailPrice":null,"UKRetailPrice":null,"CARetailPrice":null,"DERetailPrice":null,"USDateAdded":null,"USDateRemoved":null,"Pieces":44,"Minifigs":null,"MinifigNumbers":null,"PackagingType":null,"Availability":null,"USItemNumber":null,"EUItemNumber":null,"EAN":null,"UPC":null,"Width":null,"Height":null,"Depth":null,"Weight":null,"ModelDimension1":null,"ModelDimension2":null,"ModelDimension3":null,"AgeMin":null,"AgeMax":null,"OwnCount":null,"WantCount":null,"InstructionsCount":null,"AdditionalImageCount":null,"Released":null,"Rating":null,"BrickLinkSoldPriceNew":null,"BrickLinkSoldPriceUsed":null,"Designers":null,"LaunchDate":null,"ExitDate":null,"link":"https://www.bricklink.com/v2/catalog/catalogitem.page?S=40345-1#T=P","productImage":"https://cdn.rebrickable.com/media/sets/40345-1.jpg","instructionsLink":"","type":"Set","New":null,"Used":null,"ExclusiveMinifigNumbers":null,"ExclusiveMinifigCount":null,"CurrentRRPBaseline":null},{"SetID":65850,"Number":60224,"Variant":1,"YearFrom":2019,"Category":"Normal","Theme":"Mars Exploration","ThemeGroup":"City","Subtheme":null,"SetName":"Satellite Service Mission","Image":"X","ImageFilename":"60224-1","USRetailPrice":null,"UKRetailPrice":null,"CARetailPrice":null,"DERetailPrice":null,"USDateAdded":null,"USDateRemoved":null,"Pieces":84,"Minifigs":null,"MinifigNumbers":null,"PackagingType":null,"Availability":null,"USItemNumber":null,"EUItemNumber":null,"EAN":null,"UPC":null,"Width":null,"Height":null,"Depth":null,"Weight":null,"ModelDimension1":null,"ModelDimension2":null,"ModelDimension3":null,"AgeMin":null,"AgeMax":null,"OwnCount":null,"WantCount":null,"InstructionsCount":null,"AdditionalImageCount":null,"Released":null,"Rating":null,"BrickLinkSoldPriceNew":null,"BrickLinkSoldPriceUsed":null,"Designers":null,"LaunchDate":null,"ExitDate":null,"link":"https://www.bricklink.com/v2/catalog/catalogitem.page?S=60224-1#T=P","productImage":"https://cdn.rebrickable.com/media/sets/60224-1.jpg","instructionsLink":"","type":"Set","New":null,"Used":null,"ExclusiveMinifigNumbers":null,"ExclusiveMinifigCount":null,"CurrentRRPBaseline":null},{"SetID":65851,"Number":60225,"Variant":1,"YearFrom":2019,"Category":"Normal","Theme":"Mars Exploration","ThemeGroup":"City","Subtheme":null,"SetName":"Rover Testing Drive","Image":"X","ImageFilename":"60225-1","USRetailPrice":null,"UKRetailPrice":null,"CARetailPrice":null,"DERetailPrice":null,"USDateAdded":null,"USDateRemoved":null,"Pieces":202,"Minifigs":null,"MinifigNumbers":null,"PackagingType":null,"Availability":null,"USItemNumber":null,"EUItemNumber":null,"EAN":null,"UPC":null,"Width":null,"Height":null,"Depth":null,"Weight":null,"ModelDimension1":null,"ModelDimension2":null,"ModelDimension3":null,"AgeMin":null,"AgeMax":null,"OwnCount":null,"WantCount":null,"InstructionsCount":null,"AdditionalImageCount":null,"Released":null,"Rating":null,"BrickLinkSoldPriceNew":null,"BrickLinkSoldPriceUsed":null,"Designers":null,"LaunchDate":null,"ExitDate":null,"link":"https://www.bricklink.com/v2/catalog/catalogitem.page?S=60225-1#T=P","productImage":"https://cdn.rebrickable.com/media/sets/60225-1.jpg","instructionsLink":"","type":"Set","New":null,"Used":null,"ExclusiveMinifigNumbers":null,"ExclusiveMinifigCount":null,"CurrentRRPBaseline":null},{"SetID":65852,"Number":60226,"Variant":1,"YearFrom":2019,"Category":"Normal","Theme":"Mars Exploration","ThemeGroup":"City","Subtheme":null,"SetName":"Mars Research Shuttle","Image":"X","ImageFilename":"60226-1","USRetailPrice":null,"UKRetailPrice":null,"CARetailPrice":null,"DERetailPrice":null,"USDateAdded":null,"USDateRemoved":null,"Pieces":273,"Minifigs":null,"MinifigNumbers":null,"PackagingType":null,"Availability":null,"USItemNumber":null,"EUItemNumber":null,"EAN":null,"UPC":null,"Width":null,"Height":null,"Depth":null,"Weight":null,"ModelDimension1":null,"ModelDimension2":null,"ModelDimension3":null,"AgeMin":null,"AgeMax":null,"OwnCount":null,"WantCount":null,"InstructionsCount":null,"AdditionalImageCount":null,"Released":null,"Rating":null,"BrickLinkSoldPriceNew":null,"BrickLinkSoldPriceUsed":null,"Designers":null,"LaunchDate":null,"ExitDate":null,"link":"https://www.bricklink.com/v2/catalog/catalogitem.page?S=60226-1#T=P","productImage":"https://cdn.rebrickable.com/media/sets/60226-1.jpg","instructionsLink":"","type":"Set","New":null,"Used":null,"ExclusiveMinifigNumbers":null,"ExclusiveMinifigCount":null,"CurrentRRPBaseline":null},{"SetID":65853,"Number":60227,"Variant":1,"YearFrom":2019,"Category":"Normal","Theme":"Mars Exploration","ThemeGroup":"City","Subtheme":null,"SetName":"Lunar Space Station","Image":"X","ImageFilename":"60227-1","USRetailPrice":null,"UKRetailPrice":null,"CARetailPrice":null,"DERetailPrice":null,"USDateAdded":null,"USDateRemoved":null,"Pieces":417,"Minifigs":null,"MinifigNumbers":null,"PackagingType":null,"Availability":null,"USItemNumber":null,"EUItemNumber":null,"EAN":null,"UPC":null,"Width":null,"Height":null,"Depth":null,"Weight":null,"ModelDimension1":null,"ModelDimension2":null,"ModelDimension3":null,"AgeMin":null,"AgeMax":null,"OwnCount":null,"WantCount":null,"InstructionsCount":null,"AdditionalImageCount":null,"Released":null,"Rating":null,"BrickLinkSoldPriceNew":null,"BrickLinkSoldPriceUsed":null,"Designers":null,"LaunchDate":null,"ExitDate":null,"link":"https://www.bricklink.com/v2/catalog/catalogitem.page?S=60227-1#T=P","productImage":"https://cdn.rebrickable.com/media/sets/60227-1.jpg","instructionsLink":"","type":"Set","New":null,"Used":null,"ExclusiveMinifigNumbers":null,"ExclusiveMinifigCount":null,"CurrentRRPBaseline":null},{"SetID":65854,"Number":60228,"Variant":1,"YearFrom":2019,"Category":"Normal","Theme":"Mars Exploration","ThemeGroup":"City","Subtheme":null,"SetName":"Deep Space Rocket and Launch Control","Image":"X","ImageFilename":"60228-1","USRetailPrice":null,"UKRetailPrice":null,"CARetailPrice":null,"DERetailPrice":null,"USDateAdded":null,"USDateRemoved":null,"Pieces":837,"Minifigs":null,"MinifigNumbers":null,"PackagingType":null,"Availability":null,"USItemNumber":null,"EUItemNumber":null,"EAN":null,"UPC":null,"Width":null,"Height":null,"Depth":null,"Weight":null,"ModelDimension1":null,"ModelDimension2":null,"ModelDimension3":null,"AgeMin":null,"AgeMax":null,"OwnCount":null,"WantCount":null,"InstructionsCount":null,"AdditionalImageCount":null,"Released":null,"Rating":null,"BrickLinkSoldPriceNew":null,"BrickLinkSoldPriceUsed":null,"Designers":null,"LaunchDate":null,"ExitDate":null,"link":"https://www.bricklink.com/v2/catalog/catalogitem.page?S=60228-1#T=P","productImage":"https://cdn.rebrickable.com/media/sets/60228-1.jpg","instructionsLink":"","type":"Set","New":null,"Used":null,"ExclusiveMinifigNumbers":null,"ExclusiveMinifigCount":null,"CurrentRRPBaseline":null},{"SetID":65855,"Number":60229,"Variant":1,"YearFrom":2019,"Category":"Normal","Theme":"Mars Exploration","ThemeGroup":"City","Subtheme":null,"SetName":"Rocket Assembly & Transport","Image":"X","ImageFilename":"60229-1","USRetailPrice":null,"UKRetailPrice":null,"CARetailPrice":null,"DERetailPrice":null,"USDateAdded":null,"USDateRemoved":null,"Pieces":1062,"Minifigs":null,"MinifigNumbers":null,"PackagingType":null,"Availability":null,"USItemNumber":null,"EUItemNumber":null,"EAN":null,"UPC":null,"Width":null,"Height":null,"Depth":null,"Weight":null,"ModelDimension1":null,"ModelDimension2":null,"ModelDimension3":null,"AgeMin":null,"AgeMax":null,"OwnCount":null,"WantCount":null,"InstructionsCount":null,"AdditionalImageCount":null,"Released":null,"Rating":null,"BrickLinkSoldPriceNew":null,"BrickLinkSoldPriceUsed":null,"Designers":null,"LaunchDate":null,"ExitDate":null,"link":"https://www.bricklink.com/v2/catalog/catalogitem.page?S=60229-1#T=P","productImage":"https://cdn.rebrickable.com/media/sets/60229-1.jpg","instructionsLink":"","type":"Set","New":null,"Used":null,"ExclusiveMinifigNumbers":null,"ExclusiveMinifigCount":null,"CurrentRRPBaseline":null},{"SetID":65856,"Number":60230,"Variant":1,"YearFrom":2019,"Category":"Normal","Theme":"Mars Exploration","ThemeGroup":"City","Subtheme":null,"SetName":"People Pack – Space Research and Development","Image":"X","ImageFilename":"60230-1","USRetailPrice":null,"UKRetailPrice":null,"CARetailPrice":null,"DERetailPrice":null,"USDateAdded":null,"USDateRemoved":null,"Pieces":209,"Minifigs":null,"MinifigNumbers":null,"PackagingType":null,"Availability":null,"USItemNumber":null,"EUItemNumber":null,"EAN":null,"UPC":null,"Width":null,"Height":null,"Depth":null,"Weight":null,"ModelDimension1":null,"ModelDimension2":null,"ModelDimension3":null,"AgeMin":null,"AgeMax":null,"OwnCount":null,"WantCount":null,"InstructionsCount":null,"AdditionalImageCount":null,"Released":null,"Rating":null,"BrickLinkSoldPriceNew":null,"BrickLinkSoldPriceUsed":null,"Designers":null,"LaunchDate":null,"ExitDate":null,"link":"https://www.bricklink.com/v2/catalog/catalogitem.page?S=60230-1#T=P","productImage":"https://cdn.rebrickable.com/media/sets/60230-1.jpg","instructionsLink":"","type":"Set","New":null,"Used":null,"ExclusiveMinifigNumbers":null,"ExclusiveMinifigCount":null,"CurrentRRPBaseline":null},{"SetID":67513,"Number":66645,"Variant":1,"YearFrom":2020,"Category":"Normal","Theme":"Mars Exploration","ThemeGroup":"City","Subtheme":null,"SetName":"City Space Bundle","Image":"X","ImageFilename":"66645-1","USRetailPrice":null,"UKRetailPrice":null,"CARetailPrice":null,"DERetailPrice":null,"USDateAdded":null,"USDateRemoved":null,"Pieces":0,"Minifigs":null,"MinifigNumbers":null,"PackagingType":null,"Availability":null,"USItemNumber":null,"EUItemNumber":null,"EAN":null,"UPC":null,"Width":null,"Height":null,"Depth":null,"Weight":null,"ModelDimension1":null,"ModelDimension2":null,"ModelDimension3":null,"AgeMin":null,"AgeMax":null,"OwnCount":null,"WantCount":null,"InstructionsCount":null,"AdditionalImageCount":null,"Released":null,"Rating":null,"BrickLinkSoldPriceNew":null,"BrickLinkSoldPriceUsed":null,"Designers":null,"LaunchDate":null,"ExitDate":null,"link":"https://www.bricklink.com/v2/catalog/catalogitem.page?S=66645-1#T=P","productImage":"https://cdn.rebrickable.com/media/sets/66645-1.jpg","instructionsLink":"","type":"Set","New":null,"Used":null,"ExclusiveMinifigNumbers":null,"ExclusiveMinifigCount":null,"CurrentRRPBaseline":null},{"SetID":74138,"Number":951908,"Variant":1,"YearFrom":2019,"Category":"Normal","Theme":"Mars Exploration","ThemeGroup":"City","Subtheme":null,"SetName":"Astronaut","Image":"X","ImageFilename":"951908-1","USRetailPrice":null,"UKRetailPrice":null,"CARetailPrice":null,"DERetailPrice":null,"USDateAdded":null,"USDateRemoved":null,"Pieces":18,"Minifigs":null,"MinifigNumbers":null,"PackagingType":null,"Availability":null,"USItemNumber":null,"EUItemNumber":null,"EAN":null,"UPC":null,"Width":null,"Height":null,"Depth":null,"Weight":null,"ModelDimension1":null,"ModelDimension2":null,"ModelDimension3":null,"AgeMin":null,"AgeMax":null,"OwnCount":null,"WantCount":null,"InstructionsCount":null,"AdditionalImageCount":null,"Released":null,"Rating":null,"BrickLinkSoldPriceNew":null,"BrickLinkSoldPriceUsed":null,"Designers":null,"LaunchDate":null,"ExitDate":null,"link":"https://www.bricklink.com/v2/catalog/catalogitem.page?S=951908-1#T=P","productImage":"https://cdn.rebrickable.com/media/sets/951908-1.jpg","instructionsLink":"","type":"Set","New":null,"Used":null,"ExclusiveMinifigNumbers":null,"ExclusiveMinifigCount":null,"CurrentRRPBaseline":null},{"SetID":74141,"Number":951911,"Variant":1,"YearFrom":2019,"Category":"Normal","Theme":"Mars Exploration","ThemeGroup":"City","Subtheme":null,"SetName":"Rover","Image":"X","ImageFilename":"951911-1","USRetailPrice":null,"UKRetailPrice":null,"CARetailPrice":null,"DERetailPrice":null,"USDateAdded":null,"USDateRemoved":null,"Pieces":23,"Minifigs":null,"MinifigNumbers":null,"PackagingType":null,"Availability":null,"USItemNumber":null,"EUItemNumber":null,"EAN":null,"UPC":null,"Width":null,"Height":null,"Depth":null,"Weight":null,"ModelDimension1":null,"ModelDimension2":null,"ModelDimension3":null,"AgeMin":null,"AgeMax":null,"OwnCount":null,"WantCount":null,"InstructionsCount":null,"AdditionalImageCount":null,"Released":null,"Rating":null,"BrickLinkSoldPriceNew":null,"BrickLinkSoldPriceUsed":null,"Designers":null,"LaunchDate":null,"ExitDate":null,"link":"https://www.bricklink.com/v2/catalog/catalogitem.page?S=951911-1#T=P","productImage":"https://cdn.rebrickable.com/media/sets/951911-1.jpg","instructionsLink":"","type":"Set","New":null,"Used":null,"ExclusiveMinifigNumbers":null,"ExclusiveMinifigCount":null,"CurrentRRPBaseline":null}]