[{"SetID":58235,"Number":3850001,"Variant":1,"YearFrom":2015,"Category":"Normal","Theme":"Pick A Model","ThemeGroup":"LEGO Brand Store","Subtheme":null,"SetName":"Crocodile","Image":"X","ImageFilename":"3850001-1","USRetailPrice":null,"UKRetailPrice":null,"CARetailPrice":null,"DERetailPrice":null,"USDateAdded":null,"USDateRemoved":null,"Pieces":30,"Minifigs":null,"MinifigNumbers":null,"PackagingType":null,"Availability":null,"USItemNumber":null,"EUItemNumber":null,"EAN":null,"UPC":null,"Width":null,"Height":null,"Depth":null,"Weight":null,"ModelDimension1":null,"ModelDimension2":null,"ModelDimension3":null,"AgeMin":null,"AgeMax":null,"OwnCount":null,"WantCount":null,"InstructionsCount":null,"AdditionalImageCount":null,"Released":null,"Rating":null,"BrickLinkSoldPriceNew":null,"BrickLinkSoldPriceUsed":null,"Designers":null,"LaunchDate":null,"ExitDate":null,"link":"https://www.bricklink.com/v2/catalog/catalogitem.page?S=3850001-1#T=P","productImage":"https://cdn.rebrickable.com/media/sets/3850001-1.jpg","instructionsLink":"","type":"Set","New":null,"Used":null,"ExclusiveMinifigNumbers":null,"ExclusiveMinifigCount":null,"CurrentRRPBaseline":null},{"SetID":58236,"Number":3850002,"Variant":1,"YearFrom":2015,"Category":"Normal","Theme":"Pick A Model","ThemeGroup":"LEGO Brand Store","Subtheme":null,"SetName":"Car","Image":"X","ImageFilename":"3850002-1","USRetailPrice":null,"UKRetailPrice":null,"CARetailPrice":null,"DERetailPrice":null,"USDateAdded":null,"USDateRemoved":null,"Pieces":40,"Minifigs":null,"MinifigNumbers":null,"PackagingType":null,"Availability":null,"USItemNumber":null,"EUItemNumber":null,"EAN":null,"UPC":null,"Width":null,"Height":null,"Depth":null,"Weight":null,"ModelDimension1":null,"ModelDimension2":null,"ModelDimension3":null,"AgeMin":null,"AgeMax":null,"OwnCount":null,"WantCount":null,"InstructionsCount":null,"AdditionalImageCount":null,"Released":null,"Rating":null,"BrickLinkSoldPriceNew":null,"BrickLinkSoldPriceUsed":null,"Designers":null,"LaunchDate":null,"ExitDate":null,"link":"https://www.bricklink.com/v2/catalog/catalogitem.page?S=3850002-1#T=P","productImage":"https://cdn.rebrickable.com/media/sets/3850002-1.jpg","instructionsLink":"","type":"Set","New":null,"Used":null,"ExclusiveMinifigNumbers":null,"ExclusiveMinifigCount":null,"CurrentRRPBaseline":null},{"SetID":58237,"Number":3850003,"Variant":1,"YearFrom":2015,"Category":"Normal","Theme":"Pick A Model","ThemeGroup":"LEGO Brand Store","Subtheme":null,"SetName":"Giraffes","Image":"X","ImageFilename":"3850003-1","USRetailPrice":null,"UKRetailPrice":null,"CARetailPrice":null,"DERetailPrice":null,"USDateAdded":null,"USDateRemoved":null,"Pieces":36,"Minifigs":null,"MinifigNumbers":null,"PackagingType":null,"Availability":null,"USItemNumber":null,"EUItemNumber":null,"EAN":null,"UPC":null,"Width":null,"Height":null,"Depth":null,"Weight":null,"ModelDimension1":null,"ModelDimension2":null,"ModelDimension3":null,"AgeMin":null,"AgeMax":null,"OwnCount":null,"WantCount":null,"InstructionsCount":null,"AdditionalImageCount":null,"Released":null,"Rating":null,"BrickLinkSoldPriceNew":null,"BrickLinkSoldPriceUsed":null,"Designers":null,"LaunchDate":null,"ExitDate":null,"link":"https://www.bricklink.com/v2/catalog/catalogitem.page?S=3850003-1#T=P","productImage":"https://cdn.rebrickable.com/media/sets/3850003-1.jpg","instructionsLink":"","type":"Set","New":null,"Used":null,"ExclusiveMinifigNumbers":null,"ExclusiveMinifigCount":null,"CurrentRRPBaseline":null},{"SetID":58238,"Number":3850004,"Variant":1,"YearFrom":2015,"Category":"Normal","Theme":"Pick A Model","ThemeGroup":"LEGO Brand Store","Subtheme":null,"SetName":"Biplane","Image":"X","ImageFilename":"3850004-1","USRetailPrice":null,"UKRetailPrice":null,"CARetailPrice":null,"DERetailPrice":null,"USDateAdded":null,"USDateRemoved":null,"Pieces":24,"Minifigs":null,"MinifigNumbers":null,"PackagingType":null,"Availability":null,"USItemNumber":null,"EUItemNumber":null,"EAN":null,"UPC":null,"Width":null,"Height":null,"Depth":null,"Weight":null,"ModelDimension1":null,"ModelDimension2":null,"ModelDimension3":null,"AgeMin":null,"AgeMax":null,"OwnCount":null,"WantCount":null,"InstructionsCount":null,"AdditionalImageCount":null,"Released":null,"Rating":null,"BrickLinkSoldPriceNew":null,"BrickLinkSoldPriceUsed":null,"Designers":null,"LaunchDate":null,"ExitDate":null,"link":"https://www.bricklink.com/v2/catalog/catalogitem.page?S=3850004-1#T=P","productImage":"https://cdn.rebrickable.com/media/sets/3850004-1.jpg","instructionsLink":"","type":"Set","New":null,"Used":null,"ExclusiveMinifigNumbers":null,"ExclusiveMinifigCount":null,"CurrentRRPBaseline":null},{"SetID":58239,"Number":3850005,"Variant":1,"YearFrom":2015,"Category":"Normal","Theme":"Pick A Model","ThemeGroup":"LEGO Brand Store","Subtheme":null,"SetName":"Panda","Image":"X","ImageFilename":"3850005-1","USRetailPrice":null,"UKRetailPrice":null,"CARetailPrice":null,"DERetailPrice":null,"USDateAdded":null,"USDateRemoved":null,"Pieces":35,"Minifigs":null,"MinifigNumbers":null,"PackagingType":null,"Availability":null,"USItemNumber":null,"EUItemNumber":null,"EAN":null,"UPC":null,"Width":null,"Height":null,"Depth":null,"Weight":null,"ModelDimension1":null,"ModelDimension2":null,"ModelDimension3":null,"AgeMin":null,"AgeMax":null,"OwnCount":null,"WantCount":null,"InstructionsCount":null,"AdditionalImageCount":null,"Released":null,"Rating":null,"BrickLinkSoldPriceNew":null,"BrickLinkSoldPriceUsed":null,"Designers":null,"LaunchDate":null,"ExitDate":null,"link":"https://www.bricklink.com/v2/catalog/catalogitem.page?S=3850005-1#T=P","productImage":"https://cdn.rebrickable.com/media/sets/3850005-1.jpg","instructionsLink":"","type":"Set","New":null,"Used":null,"ExclusiveMinifigNumbers":null,"ExclusiveMinifigCount":null,"CurrentRRPBaseline":null},{"SetID":58240,"Number":3850006,"Variant":1,"YearFrom":2015,"Category":"Normal","Theme":"Pick A Model","ThemeGroup":"LEGO Brand Store","Subtheme":null,"SetName":"Jeep","Image":"X","ImageFilename":"3850006-1","USRetailPrice":null,"UKRetailPrice":null,"CARetailPrice":null,"DERetailPrice":null,"USDateAdded":null,"USDateRemoved":null,"Pieces":29,"Minifigs":null,"MinifigNumbers":null,"PackagingType":null,"Availability":null,"USItemNumber":null,"EUItemNumber":null,"EAN":null,"UPC":null,"Width":null,"Height":null,"Depth":null,"Weight":null,"ModelDimension1":null,"ModelDimension2":null,"ModelDimension3":null,"AgeMin":null,"AgeMax":null,"OwnCount":null,"WantCount":null,"InstructionsCount":null,"AdditionalImageCount":null,"Released":null,"Rating":null,"BrickLinkSoldPriceNew":null,"BrickLinkSoldPriceUsed":null,"Designers":null,"LaunchDate":null,"ExitDate":null,"link":"https://www.bricklink.com/v2/catalog/catalogitem.page?S=3850006-1#T=P","productImage":"https://cdn.rebrickable.com/media/sets/3850006-1.jpg","instructionsLink":"","type":"Set","New":null,"Used":null,"ExclusiveMinifigNumbers":null,"ExclusiveMinifigCount":null,"CurrentRRPBaseline":null},{"SetID":58241,"Number":3850007,"Variant":1,"YearFrom":2016,"Category":"Normal","Theme":"Pick A Model","ThemeGroup":"LEGO Brand Store","Subtheme":null,"SetName":"Elephant","Image":"X","ImageFilename":"3850007-1","USRetailPrice":null,"UKRetailPrice":null,"CARetailPrice":null,"DERetailPrice":null,"USDateAdded":null,"USDateRemoved":null,"Pieces":27,"Minifigs":null,"MinifigNumbers":null,"PackagingType":null,"Availability":null,"USItemNumber":null,"EUItemNumber":null,"EAN":null,"UPC":null,"Width":null,"Height":null,"Depth":null,"Weight":null,"ModelDimension1":null,"ModelDimension2":null,"ModelDimension3":null,"AgeMin":null,"AgeMax":null,"OwnCount":null,"WantCount":null,"InstructionsCount":null,"AdditionalImageCount":null,"Released":null,"Rating":null,"BrickLinkSoldPriceNew":null,"BrickLinkSoldPriceUsed":null,"Designers":null,"LaunchDate":null,"ExitDate":null,"link":"https://www.bricklink.com/v2/catalog/catalogitem.page?S=3850007-1#T=P","productImage":"https://cdn.rebrickable.com/media/sets/3850007-1.jpg","instructionsLink":"","type":"Set","New":null,"Used":null,"ExclusiveMinifigNumbers":null,"ExclusiveMinifigCount":null,"CurrentRRPBaseline":null},{"SetID":58242,"Number":3850008,"Variant":1,"YearFrom":2016,"Category":"Normal","Theme":"Pick A Model","ThemeGroup":"LEGO Brand Store","Subtheme":null,"SetName":"Jet","Image":"X","ImageFilename":"3850008-1","USRetailPrice":null,"UKRetailPrice":null,"CARetailPrice":null,"DERetailPrice":null,"USDateAdded":null,"USDateRemoved":null,"Pieces":18,"Minifigs":null,"MinifigNumbers":null,"PackagingType":null,"Availability":null,"USItemNumber":null,"EUItemNumber":null,"EAN":null,"UPC":null,"Width":null,"Height":null,"Depth":null,"Weight":null,"ModelDimension1":null,"ModelDimension2":null,"ModelDimension3":null,"AgeMin":null,"AgeMax":null,"OwnCount":null,"WantCount":null,"InstructionsCount":null,"AdditionalImageCount":null,"Released":null,"Rating":null,"BrickLinkSoldPriceNew":null,"BrickLinkSoldPriceUsed":null,"Designers":null,"LaunchDate":null,"ExitDate":null,"link":"https://www.bricklink.com/v2/catalog/catalogitem.page?S=3850008-1#T=P","productImage":"https://cdn.rebrickable.com/media/sets/3850008-1.jpg","instructionsLink":"","type":"Set","New":null,"Used":null,"ExclusiveMinifigNumbers":null,"ExclusiveMinifigCount":null,"CurrentRRPBaseline":null},{"SetID":58243,"Number":3850009,"Variant":1,"YearFrom":2016,"Category":"Normal","Theme":"Pick A Model","ThemeGroup":"LEGO Brand Store","Subtheme":null,"SetName":"Aircraft","Image":"X","ImageFilename":"3850009-1","USRetailPrice":null,"UKRetailPrice":null,"CARetailPrice":null,"DERetailPrice":null,"USDateAdded":null,"USDateRemoved":null,"Pieces":41,"Minifigs":null,"MinifigNumbers":null,"PackagingType":null,"Availability":null,"USItemNumber":null,"EUItemNumber":null,"EAN":null,"UPC":null,"Width":null,"Height":null,"Depth":null,"Weight":null,"ModelDimension1":null,"ModelDimension2":null,"ModelDimension3":null,"AgeMin":null,"AgeMax":null,"OwnCount":null,"WantCount":null,"InstructionsCount":null,"AdditionalImageCount":null,"Released":null,"Rating":null,"BrickLinkSoldPriceNew":null,"BrickLinkSoldPriceUsed":null,"Designers":null,"LaunchDate":null,"ExitDate":null,"link":"https://www.bricklink.com/v2/catalog/catalogitem.page?S=3850009-1#T=P","productImage":"https://cdn.rebrickable.com/media/sets/3850009-1.jpg","instructionsLink":"","type":"Set","New":null,"Used":null,"ExclusiveMinifigNumbers":null,"ExclusiveMinifigCount":null,"CurrentRRPBaseline":null},{"SetID":58244,"Number":3850010,"Variant":1,"YearFrom":2016,"Category":"Normal","Theme":"Pick A Model","ThemeGroup":"LEGO Brand Store","Subtheme":null,"SetName":"Butterfly","Image":"X","ImageFilename":"3850010-1","USRetailPrice":null,"UKRetailPrice":null,"CARetailPrice":null,"DERetailPrice":null,"USDateAdded":null,"USDateRemoved":null,"Pieces":45,"Minifigs":null,"MinifigNumbers":null,"PackagingType":null,"Availability":null,"USItemNumber":null,"EUItemNumber":null,"EAN":null,"UPC":null,"Width":null,"Height":null,"Depth":null,"Weight":null,"ModelDimension1":null,"ModelDimension2":null,"ModelDimension3":null,"AgeMin":null,"AgeMax":null,"OwnCount":null,"WantCount":null,"InstructionsCount":null,"AdditionalImageCount":null,"Released":null,"Rating":null,"BrickLinkSoldPriceNew":null,"BrickLinkSoldPriceUsed":null,"Designers":null,"LaunchDate":null,"ExitDate":null,"link":"https://www.bricklink.com/v2/catalog/catalogitem.page?S=3850010-1#T=P","productImage":"https://cdn.rebrickable.com/media/sets/3850010-1.jpg","instructionsLink":"","type":"Set","New":null,"Used":null,"ExclusiveMinifigNumbers":null,"ExclusiveMinifigCount":null,"CurrentRRPBaseline":null},{"SetID":58245,"Number":3850011,"Variant":1,"YearFrom":2016,"Category":"Normal","Theme":"Pick A Model","ThemeGroup":"LEGO Brand Store","Subtheme":null,"SetName":"Statue of Liberty","Image":"X","ImageFilename":"3850011-1","USRetailPrice":null,"UKRetailPrice":null,"CARetailPrice":null,"DERetailPrice":null,"USDateAdded":null,"USDateRemoved":null,"Pieces":58,"Minifigs":null,"MinifigNumbers":null,"PackagingType":null,"Availability":null,"USItemNumber":null,"EUItemNumber":null,"EAN":null,"UPC":null,"Width":null,"Height":null,"Depth":null,"Weight":null,"ModelDimension1":null,"ModelDimension2":null,"ModelDimension3":null,"AgeMin":null,"AgeMax":null,"OwnCount":null,"WantCount":null,"InstructionsCount":null,"AdditionalImageCount":null,"Released":null,"Rating":null,"BrickLinkSoldPriceNew":null,"BrickLinkSoldPriceUsed":null,"Designers":null,"LaunchDate":null,"ExitDate":null,"link":"https://www.bricklink.com/v2/catalog/catalogitem.page?S=3850011-1#T=P","productImage":"https://cdn.rebrickable.com/media/sets/3850011-1.jpg","instructionsLink":"","type":"Set","New":null,"Used":null,"ExclusiveMinifigNumbers":null,"ExclusiveMinifigCount":null,"CurrentRRPBaseline":null},{"SetID":58246,"Number":3850012,"Variant":1,"YearFrom":2016,"Category":"Normal","Theme":"Pick A Model","ThemeGroup":"LEGO Brand Store","Subtheme":null,"SetName":"Truck","Image":"X","ImageFilename":"3850012-1","USRetailPrice":null,"UKRetailPrice":null,"CARetailPrice":null,"DERetailPrice":null,"USDateAdded":null,"USDateRemoved":null,"Pieces":66,"Minifigs":null,"MinifigNumbers":null,"PackagingType":null,"Availability":null,"USItemNumber":null,"EUItemNumber":null,"EAN":null,"UPC":null,"Width":null,"Height":null,"Depth":null,"Weight":null,"ModelDimension1":null,"ModelDimension2":null,"ModelDimension3":null,"AgeMin":null,"AgeMax":null,"OwnCount":null,"WantCount":null,"InstructionsCount":null,"AdditionalImageCount":null,"Released":null,"Rating":null,"BrickLinkSoldPriceNew":null,"BrickLinkSoldPriceUsed":null,"Designers":null,"LaunchDate":null,"ExitDate":null,"link":"https://www.bricklink.com/v2/catalog/catalogitem.page?S=3850012-1#T=P","productImage":"https://cdn.rebrickable.com/media/sets/3850012-1.jpg","instructionsLink":"","type":"Set","New":null,"Used":null,"ExclusiveMinifigNumbers":null,"ExclusiveMinifigCount":null,"CurrentRRPBaseline":null},{"SetID":58247,"Number":3850013,"Variant":1,"YearFrom":2016,"Category":"Normal","Theme":"Pick A Model","ThemeGroup":"LEGO Brand Store","Subtheme":null,"SetName":"Turtle","Image":"X","ImageFilename":"3850013-1","USRetailPrice":null,"UKRetailPrice":null,"CARetailPrice":null,"DERetailPrice":null,"USDateAdded":null,"USDateRemoved":null,"Pieces":50,"Minifigs":null,"MinifigNumbers":null,"PackagingType":null,"Availability":null,"USItemNumber":null,"EUItemNumber":null,"EAN":null,"UPC":null,"Width":null,"Height":null,"Depth":null,"Weight":null,"ModelDimension1":null,"ModelDimension2":null,"ModelDimension3":null,"AgeMin":null,"AgeMax":null,"OwnCount":null,"WantCount":null,"InstructionsCount":null,"AdditionalImageCount":null,"Released":null,"Rating":null,"BrickLinkSoldPriceNew":null,"BrickLinkSoldPriceUsed":null,"Designers":null,"LaunchDate":null,"ExitDate":null,"link":"https://www.bricklink.com/v2/catalog/catalogitem.page?S=3850013-1#T=P","productImage":"https://cdn.rebrickable.com/media/sets/3850013-1.jpg","instructionsLink":"","type":"Set","New":null,"Used":null,"ExclusiveMinifigNumbers":null,"ExclusiveMinifigCount":null,"CurrentRRPBaseline":null},{"SetID":58248,"Number":3850014,"Variant":1,"YearFrom":2016,"Category":"Normal","Theme":"Pick A Model","ThemeGroup":"LEGO Brand Store","Subtheme":null,"SetName":"Snowplough","Image":"X","ImageFilename":"3850014-1","USRetailPrice":null,"UKRetailPrice":null,"CARetailPrice":null,"DERetailPrice":null,"USDateAdded":null,"USDateRemoved":null,"Pieces":44,"Minifigs":null,"MinifigNumbers":null,"PackagingType":null,"Availability":null,"USItemNumber":null,"EUItemNumber":null,"EAN":null,"UPC":null,"Width":null,"Height":null,"Depth":null,"Weight":null,"ModelDimension1":null,"ModelDimension2":null,"ModelDimension3":null,"AgeMin":null,"AgeMax":null,"OwnCount":null,"WantCount":null,"InstructionsCount":null,"AdditionalImageCount":null,"Released":null,"Rating":null,"BrickLinkSoldPriceNew":null,"BrickLinkSoldPriceUsed":null,"Designers":null,"LaunchDate":null,"ExitDate":null,"link":"https://www.bricklink.com/v2/catalog/catalogitem.page?S=3850014-1#T=P","productImage":"https://cdn.rebrickable.com/media/sets/3850014-1.jpg","instructionsLink":"","type":"Set","New":null,"Used":null,"ExclusiveMinifigNumbers":null,"ExclusiveMinifigCount":null,"CurrentRRPBaseline":null},{"SetID":58249,"Number":3850015,"Variant":1,"YearFrom":2016,"Category":"Normal","Theme":"Pick A Model","ThemeGroup":"LEGO Brand Store","Subtheme":null,"SetName":"Penguins","Image":"X","ImageFilename":"3850015-1","USRetailPrice":null,"UKRetailPrice":null,"CARetailPrice":null,"DERetailPrice":null,"USDateAdded":null,"USDateRemoved":null,"Pieces":39,"Minifigs":null,"MinifigNumbers":null,"PackagingType":null,"Availability":null,"USItemNumber":null,"EUItemNumber":null,"EAN":null,"UPC":null,"Width":null,"Height":null,"Depth":null,"Weight":null,"ModelDimension1":null,"ModelDimension2":null,"ModelDimension3":null,"AgeMin":null,"AgeMax":null,"OwnCount":null,"WantCount":null,"InstructionsCount":null,"AdditionalImageCount":null,"Released":null,"Rating":null,"BrickLinkSoldPriceNew":null,"BrickLinkSoldPriceUsed":null,"Designers":null,"LaunchDate":null,"ExitDate":null,"link":"https://www.bricklink.com/v2/catalog/catalogitem.page?S=3850015-1#T=P","productImage":"https://cdn.rebrickable.com/media/sets/3850015-1.jpg","instructionsLink":"","type":"Set","New":null,"Used":null,"ExclusiveMinifigNumbers":null,"ExclusiveMinifigCount":null,"CurrentRRPBaseline":null},{"SetID":58250,"Number":3850016,"Variant":1,"YearFrom":2017,"Category":"Normal","Theme":"Pick A Model","ThemeGroup":"LEGO Brand Store","Subtheme":null,"SetName":"Beaver","Image":"X","ImageFilename":"3850016-1","USRetailPrice":null,"UKRetailPrice":null,"CARetailPrice":null,"DERetailPrice":null,"USDateAdded":null,"USDateRemoved":null,"Pieces":52,"Minifigs":null,"MinifigNumbers":null,"PackagingType":null,"Availability":null,"USItemNumber":null,"EUItemNumber":null,"EAN":null,"UPC":null,"Width":null,"Height":null,"Depth":null,"Weight":null,"ModelDimension1":null,"ModelDimension2":null,"ModelDimension3":null,"AgeMin":null,"AgeMax":null,"OwnCount":null,"WantCount":null,"InstructionsCount":null,"AdditionalImageCount":null,"Released":null,"Rating":null,"BrickLinkSoldPriceNew":null,"BrickLinkSoldPriceUsed":null,"Designers":null,"LaunchDate":null,"ExitDate":null,"link":"https://www.bricklink.com/v2/catalog/catalogitem.page?S=3850016-1#T=P","productImage":"https://cdn.rebrickable.com/media/sets/3850016-1.jpg","instructionsLink":"","type":"Set","New":null,"Used":null,"ExclusiveMinifigNumbers":null,"ExclusiveMinifigCount":null,"CurrentRRPBaseline":null},{"SetID":58251,"Number":3850017,"Variant":1,"YearFrom":2017,"Category":"Normal","Theme":"Pick A Model","ThemeGroup":"LEGO Brand Store","Subtheme":null,"SetName":"Digger","Image":"X","ImageFilename":"3850017-1","USRetailPrice":null,"UKRetailPrice":null,"CARetailPrice":null,"DERetailPrice":null,"USDateAdded":null,"USDateRemoved":null,"Pieces":56,"Minifigs":null,"MinifigNumbers":null,"PackagingType":null,"Availability":null,"USItemNumber":null,"EUItemNumber":null,"EAN":null,"UPC":null,"Width":null,"Height":null,"Depth":null,"Weight":null,"ModelDimension1":null,"ModelDimension2":null,"ModelDimension3":null,"AgeMin":null,"AgeMax":null,"OwnCount":null,"WantCount":null,"InstructionsCount":null,"AdditionalImageCount":null,"Released":null,"Rating":null,"BrickLinkSoldPriceNew":null,"BrickLinkSoldPriceUsed":null,"Designers":null,"LaunchDate":null,"ExitDate":null,"link":"https://www.bricklink.com/v2/catalog/catalogitem.page?S=3850017-1#T=P","productImage":"https://cdn.rebrickable.com/media/sets/3850017-1.jpg","instructionsLink":"","type":"Set","New":null,"Used":null,"ExclusiveMinifigNumbers":null,"ExclusiveMinifigCount":null,"CurrentRRPBaseline":null},{"SetID":58252,"Number":3850031,"Variant":1,"YearFrom":2017,"Category":"Normal","Theme":"Pick A Model","ThemeGroup":"LEGO Brand Store","Subtheme":null,"SetName":"Puffin","Image":"X","ImageFilename":"3850031-1","USRetailPrice":null,"UKRetailPrice":null,"CARetailPrice":null,"DERetailPrice":null,"USDateAdded":null,"USDateRemoved":null,"Pieces":50,"Minifigs":null,"MinifigNumbers":null,"PackagingType":null,"Availability":null,"USItemNumber":null,"EUItemNumber":null,"EAN":null,"UPC":null,"Width":null,"Height":null,"Depth":null,"Weight":null,"ModelDimension1":null,"ModelDimension2":null,"ModelDimension3":null,"AgeMin":null,"AgeMax":null,"OwnCount":null,"WantCount":null,"InstructionsCount":null,"AdditionalImageCount":null,"Released":null,"Rating":null,"BrickLinkSoldPriceNew":null,"BrickLinkSoldPriceUsed":null,"Designers":null,"LaunchDate":null,"ExitDate":null,"link":"https://www.bricklink.com/v2/catalog/catalogitem.page?S=3850031-1#T=P","productImage":"https://cdn.rebrickable.com/media/sets/3850031-1.jpg","instructionsLink":"","type":"Set","New":null,"Used":null,"ExclusiveMinifigNumbers":null,"ExclusiveMinifigCount":null,"CurrentRRPBaseline":null},{"SetID":58253,"Number":3850033,"Variant":1,"YearFrom":2017,"Category":"Normal","Theme":"Pick A Model","ThemeGroup":"LEGO Brand Store","Subtheme":null,"SetName":"Guardsman","Image":"X","ImageFilename":"3850033-1","USRetailPrice":null,"UKRetailPrice":null,"CARetailPrice":null,"DERetailPrice":null,"USDateAdded":null,"USDateRemoved":null,"Pieces":44,"Minifigs":null,"MinifigNumbers":null,"PackagingType":null,"Availability":null,"USItemNumber":null,"EUItemNumber":null,"EAN":null,"UPC":null,"Width":null,"Height":null,"Depth":null,"Weight":null,"ModelDimension1":null,"ModelDimension2":null,"ModelDimension3":null,"AgeMin":null,"AgeMax":null,"OwnCount":null,"WantCount":null,"InstructionsCount":null,"AdditionalImageCount":null,"Released":null,"Rating":null,"BrickLinkSoldPriceNew":null,"BrickLinkSoldPriceUsed":null,"Designers":null,"LaunchDate":null,"ExitDate":null,"link":"https://www.bricklink.com/v2/catalog/catalogitem.page?S=3850033-1#T=P","productImage":"https://cdn.rebrickable.com/media/sets/3850033-1.jpg","instructionsLink":"","type":"Set","New":null,"Used":null,"ExclusiveMinifigNumbers":null,"ExclusiveMinifigCount":null,"CurrentRRPBaseline":null},{"SetID":58254,"Number":3850060,"Variant":1,"YearFrom":2017,"Category":"Normal","Theme":"Pick A Model","ThemeGroup":"LEGO Brand Store","Subtheme":null,"SetName":"Fish Tank","Image":"X","ImageFilename":"3850060-1","USRetailPrice":null,"UKRetailPrice":null,"CARetailPrice":null,"DERetailPrice":null,"USDateAdded":null,"USDateRemoved":null,"Pieces":33,"Minifigs":null,"MinifigNumbers":null,"PackagingType":null,"Availability":null,"USItemNumber":null,"EUItemNumber":null,"EAN":null,"UPC":null,"Width":null,"Height":null,"Depth":null,"Weight":null,"ModelDimension1":null,"ModelDimension2":null,"ModelDimension3":null,"AgeMin":null,"AgeMax":null,"OwnCount":null,"WantCount":null,"InstructionsCount":null,"AdditionalImageCount":null,"Released":null,"Rating":null,"BrickLinkSoldPriceNew":null,"BrickLinkSoldPriceUsed":null,"Designers":null,"LaunchDate":null,"ExitDate":null,"link":"https://www.bricklink.com/v2/catalog/catalogitem.page?S=3850060-1#T=P","productImage":"https://cdn.rebrickable.com/media/sets/3850060-1.jpg","instructionsLink":"","type":"Set","New":null,"Used":null,"ExclusiveMinifigNumbers":null,"ExclusiveMinifigCount":null,"CurrentRRPBaseline":null},{"SetID":58255,"Number":3850061,"Variant":1,"YearFrom":2017,"Category":"Normal","Theme":"Pick A Model","ThemeGroup":"LEGO Brand Store","Subtheme":null,"SetName":"Fish Tank #2","Image":"X","ImageFilename":"3850061-1","USRetailPrice":null,"UKRetailPrice":null,"CARetailPrice":null,"DERetailPrice":null,"USDateAdded":null,"USDateRemoved":null,"Pieces":34,"Minifigs":null,"MinifigNumbers":null,"PackagingType":null,"Availability":null,"USItemNumber":null,"EUItemNumber":null,"EAN":null,"UPC":null,"Width":null,"Height":null,"Depth":null,"Weight":null,"ModelDimension1":null,"ModelDimension2":null,"ModelDimension3":null,"AgeMin":null,"AgeMax":null,"OwnCount":null,"WantCount":null,"InstructionsCount":null,"AdditionalImageCount":null,"Released":null,"Rating":null,"BrickLinkSoldPriceNew":null,"BrickLinkSoldPriceUsed":null,"Designers":null,"LaunchDate":null,"ExitDate":null,"link":"https://www.bricklink.com/v2/catalog/catalogitem.page?S=3850061-1#T=P","productImage":"https://cdn.rebrickable.com/media/sets/3850061-1.jpg","instructionsLink":"","type":"Set","New":null,"Used":null,"ExclusiveMinifigNumbers":null,"ExclusiveMinifigCount":null,"CurrentRRPBaseline":null},{"SetID":58256,"Number":3850065,"Variant":1,"YearFrom":2018,"Category":"Normal","Theme":"Pick A Model","ThemeGroup":"LEGO Brand Store","Subtheme":null,"SetName":"Parisian Guy","Image":"X","ImageFilename":"3850065-1","USRetailPrice":null,"UKRetailPrice":null,"CARetailPrice":null,"DERetailPrice":null,"USDateAdded":null,"USDateRemoved":null,"Pieces":40,"Minifigs":null,"MinifigNumbers":null,"PackagingType":null,"Availability":null,"USItemNumber":null,"EUItemNumber":null,"EAN":null,"UPC":null,"Width":null,"Height":null,"Depth":null,"Weight":null,"ModelDimension1":null,"ModelDimension2":null,"ModelDimension3":null,"AgeMin":null,"AgeMax":null,"OwnCount":null,"WantCount":null,"InstructionsCount":null,"AdditionalImageCount":null,"Released":null,"Rating":null,"BrickLinkSoldPriceNew":null,"BrickLinkSoldPriceUsed":null,"Designers":null,"LaunchDate":null,"ExitDate":null,"link":"https://www.bricklink.com/v2/catalog/catalogitem.page?S=3850065-1#T=P","productImage":"https://cdn.rebrickable.com/media/sets/3850065-1.jpg","instructionsLink":"","type":"Set","New":null,"Used":null,"ExclusiveMinifigNumbers":null,"ExclusiveMinifigCount":null,"CurrentRRPBaseline":null},{"SetID":58257,"Number":3850070,"Variant":1,"YearFrom":2017,"Category":"Normal","Theme":"Pick A Model","ThemeGroup":"LEGO Brand Store","Subtheme":null,"SetName":"Dragon Coaster (Ollie)","Image":"X","ImageFilename":"3850070-1","USRetailPrice":null,"UKRetailPrice":null,"CARetailPrice":null,"DERetailPrice":null,"USDateAdded":null,"USDateRemoved":null,"Pieces":58,"Minifigs":null,"MinifigNumbers":null,"PackagingType":null,"Availability":null,"USItemNumber":null,"EUItemNumber":null,"EAN":null,"UPC":null,"Width":null,"Height":null,"Depth":null,"Weight":null,"ModelDimension1":null,"ModelDimension2":null,"ModelDimension3":null,"AgeMin":null,"AgeMax":null,"OwnCount":null,"WantCount":null,"InstructionsCount":null,"AdditionalImageCount":null,"Released":null,"Rating":null,"BrickLinkSoldPriceNew":null,"BrickLinkSoldPriceUsed":null,"Designers":null,"LaunchDate":null,"ExitDate":null,"link":"https://www.bricklink.com/v2/catalog/catalogitem.page?S=3850070-1#T=P","productImage":"https://cdn.rebrickable.com/media/sets/3850070-1.jpg","instructionsLink":"","type":"Set","New":null,"Used":null,"ExclusiveMinifigNumbers":null,"ExclusiveMinifigCount":null,"CurrentRRPBaseline":null},{"SetID":58258,"Number":3850072,"Variant":1,"YearFrom":2019,"Category":"Normal","Theme":"Pick A Model","ThemeGroup":"LEGO Brand Store","Subtheme":null,"SetName":"Butterfly","Image":"X","ImageFilename":"3850072-1","USRetailPrice":null,"UKRetailPrice":null,"CARetailPrice":null,"DERetailPrice":null,"USDateAdded":null,"USDateRemoved":null,"Pieces":45,"Minifigs":null,"MinifigNumbers":null,"PackagingType":null,"Availability":null,"USItemNumber":null,"EUItemNumber":null,"EAN":null,"UPC":null,"Width":null,"Height":null,"Depth":null,"Weight":null,"ModelDimension1":null,"ModelDimension2":null,"ModelDimension3":null,"AgeMin":null,"AgeMax":null,"OwnCount":null,"WantCount":null,"InstructionsCount":null,"AdditionalImageCount":null,"Released":null,"Rating":null,"BrickLinkSoldPriceNew":null,"BrickLinkSoldPriceUsed":null,"Designers":null,"LaunchDate":null,"ExitDate":null,"link":"https://www.bricklink.com/v2/catalog/catalogitem.page?S=3850072-1#T=P","productImage":"https://cdn.rebrickable.com/media/sets/3850072-1.jpg","instructionsLink":"","type":"Set","New":null,"Used":null,"ExclusiveMinifigNumbers":null,"ExclusiveMinifigCount":null,"CurrentRRPBaseline":null},{"SetID":75814,"Number":"CHICK","Variant":1,"YearFrom":2019,"Category":"Normal","Theme":"Pick A Model","ThemeGroup":"LEGO Brand Store","Subtheme":null,"SetName":"Easter Chick","Image":"X","ImageFilename":"CHICK-1","USRetailPrice":null,"UKRetailPrice":null,"CARetailPrice":null,"DERetailPrice":null,"USDateAdded":null,"USDateRemoved":null,"Pieces":18,"Minifigs":null,"MinifigNumbers":null,"PackagingType":null,"Availability":null,"USItemNumber":null,"EUItemNumber":null,"EAN":null,"UPC":null,"Width":null,"Height":null,"Depth":null,"Weight":null,"ModelDimension1":null,"ModelDimension2":null,"ModelDimension3":null,"AgeMin":null,"AgeMax":null,"OwnCount":null,"WantCount":null,"InstructionsCount":null,"AdditionalImageCount":null,"Released":null,"Rating":null,"BrickLinkSoldPriceNew":null,"BrickLinkSoldPriceUsed":null,"Designers":null,"LaunchDate":null,"ExitDate":null,"link":"https://www.bricklink.com/v2/catalog/catalogitem.page?S=CHICK-1#T=P","productImage":"https://cdn.rebrickable.com/media/sets/chick-1.jpg","instructionsLink":"","type":"Set","New":null,"Used":null,"ExclusiveMinifigNumbers":null,"ExclusiveMinifigCount":null,"CurrentRRPBaseline":null},{"SetID":76176,"Number":"GHOST","Variant":1,"YearFrom":2019,"Category":"Normal","Theme":"Pick A Model","ThemeGroup":"LEGO Brand Store","Subtheme":null,"SetName":"Ghost","Image":"X","ImageFilename":"GHOST-1","USRetailPrice":null,"UKRetailPrice":null,"CARetailPrice":null,"DERetailPrice":null,"USDateAdded":null,"USDateRemoved":null,"Pieces":21,"Minifigs":null,"MinifigNumbers":null,"PackagingType":null,"Availability":null,"USItemNumber":null,"EUItemNumber":null,"EAN":null,"UPC":null,"Width":null,"Height":null,"Depth":null,"Weight":null,"ModelDimension1":null,"ModelDimension2":null,"ModelDimension3":null,"AgeMin":null,"AgeMax":null,"OwnCount":null,"WantCount":null,"InstructionsCount":null,"AdditionalImageCount":null,"Released":null,"Rating":null,"BrickLinkSoldPriceNew":null,"BrickLinkSoldPriceUsed":null,"Designers":null,"LaunchDate":null,"ExitDate":null,"link":"https://www.bricklink.com/v2/catalog/catalogitem.page?S=GHOST-1#T=P","productImage":"https://cdn.rebrickable.com/media/sets/ghost-1.jpg","instructionsLink":"","type":"Set","New":null,"Used":null,"ExclusiveMinifigNumbers":null,"ExclusiveMinifigCount":null,"CurrentRRPBaseline":null},{"SetID":77005,"Number":"PAB4","Variant":1,"YearFrom":2012,"Category":"Normal","Theme":"Pick A Model","ThemeGroup":"LEGO Brand Store","Subtheme":null,"SetName":"Batman & Robin","Image":"X","ImageFilename":"PAB4-1","USRetailPrice":null,"UKRetailPrice":null,"CARetailPrice":null,"DERetailPrice":null,"USDateAdded":null,"USDateRemoved":null,"Pieces":96,"Minifigs":null,"MinifigNumbers":null,"PackagingType":null,"Availability":null,"USItemNumber":null,"EUItemNumber":null,"EAN":null,"UPC":null,"Width":null,"Height":null,"Depth":null,"Weight":null,"ModelDimension1":null,"ModelDimension2":null,"ModelDimension3":null,"AgeMin":null,"AgeMax":null,"OwnCount":null,"WantCount":null,"InstructionsCount":null,"AdditionalImageCount":null,"Released":null,"Rating":null,"BrickLinkSoldPriceNew":null,"BrickLinkSoldPriceUsed":null,"Designers":null,"LaunchDate":null,"ExitDate":null,"link":"https://www.bricklink.com/v2/catalog/catalogitem.page?S=PAB4-1#T=P","productImage":"https://cdn.rebrickable.com/media/sets/pab4-1.jpg","instructionsLink":"","type":"Set","New":null,"Used":null,"ExclusiveMinifigNumbers":null,"ExclusiveMinifigCount":null,"CurrentRRPBaseline":null},{"SetID":77006,"Number":"PAB7","Variant":1,"YearFrom":2012,"Category":"Normal","Theme":"Pick A Model","ThemeGroup":"LEGO Brand Store","Subtheme":null,"SetName":"Surfer","Image":"X","ImageFilename":"PAB7-1","USRetailPrice":null,"UKRetailPrice":null,"CARetailPrice":null,"DERetailPrice":null,"USDateAdded":null,"USDateRemoved":null,"Pieces":70,"Minifigs":null,"MinifigNumbers":null,"PackagingType":null,"Availability":null,"USItemNumber":null,"EUItemNumber":null,"EAN":null,"UPC":null,"Width":null,"Height":null,"Depth":null,"Weight":null,"ModelDimension1":null,"ModelDimension2":null,"ModelDimension3":null,"AgeMin":null,"AgeMax":null,"OwnCount":null,"WantCount":null,"InstructionsCount":null,"AdditionalImageCount":null,"Released":null,"Rating":null,"BrickLinkSoldPriceNew":null,"BrickLinkSoldPriceUsed":null,"Designers":null,"LaunchDate":null,"ExitDate":null,"link":"https://www.bricklink.com/v2/catalog/catalogitem.page?S=PAB7-1#T=P","productImage":"https://cdn.rebrickable.com/media/sets/pab7-1.jpg","instructionsLink":"","type":"Set","New":null,"Used":null,"ExclusiveMinifigNumbers":null,"ExclusiveMinifigCount":null,"CurrentRRPBaseline":null},{"SetID":77113,"Number":"RABBIT","Variant":1,"YearFrom":2019,"Category":"Normal","Theme":"Pick A Model","ThemeGroup":"LEGO Brand Store","Subtheme":null,"SetName":"Easter Rabbit","Image":"X","ImageFilename":"RABBIT-1","USRetailPrice":null,"UKRetailPrice":null,"CARetailPrice":null,"DERetailPrice":null,"USDateAdded":null,"USDateRemoved":null,"Pieces":26,"Minifigs":null,"MinifigNumbers":null,"PackagingType":null,"Availability":null,"USItemNumber":null,"EUItemNumber":null,"EAN":null,"UPC":null,"Width":null,"Height":null,"Depth":null,"Weight":null,"ModelDimension1":null,"ModelDimension2":null,"ModelDimension3":null,"AgeMin":null,"AgeMax":null,"OwnCount":null,"WantCount":null,"InstructionsCount":null,"AdditionalImageCount":null,"Released":null,"Rating":null,"BrickLinkSoldPriceNew":null,"BrickLinkSoldPriceUsed":null,"Designers":null,"LaunchDate":null,"ExitDate":null,"link":"https://www.bricklink.com/v2/catalog/catalogitem.page?S=RABBIT-1#T=P","productImage":"https://cdn.rebrickable.com/media/sets/rabbit-1.jpg","instructionsLink":"","type":"Set","New":null,"Used":null,"ExclusiveMinifigNumbers":null,"ExclusiveMinifigCount":null,"CurrentRRPBaseline":null},{"SetID":77143,"Number":"SANTACHIMNEY","Variant":1,"YearFrom":2019,"Category":"Normal","Theme":"Pick A Model","ThemeGroup":"LEGO Brand Store","Subtheme":null,"SetName":"Santa In A Chimney","Image":"X","ImageFilename":"SANTACHIMNEY-1","USRetailPrice":null,"UKRetailPrice":null,"CARetailPrice":null,"DERetailPrice":null,"USDateAdded":null,"USDateRemoved":null,"Pieces":24,"Minifigs":null,"MinifigNumbers":null,"PackagingType":null,"Availability":null,"USItemNumber":null,"EUItemNumber":null,"EAN":null,"UPC":null,"Width":null,"Height":null,"Depth":null,"Weight":null,"ModelDimension1":null,"ModelDimension2":null,"ModelDimension3":null,"AgeMin":null,"AgeMax":null,"OwnCount":null,"WantCount":null,"InstructionsCount":null,"AdditionalImageCount":null,"Released":null,"Rating":null,"BrickLinkSoldPriceNew":null,"BrickLinkSoldPriceUsed":null,"Designers":null,"LaunchDate":null,"ExitDate":null,"link":"https://www.bricklink.com/v2/catalog/catalogitem.page?S=SANTACHIMNEY-1#T=P","productImage":"https://cdn.rebrickable.com/media/sets/santachimney-1.jpg","instructionsLink":"","type":"Set","New":null,"Used":null,"ExclusiveMinifigNumbers":null,"ExclusiveMinifigCount":null,"CurrentRRPBaseline":null},{"SetID":77343,"Number":"VAMPIREBAT","Variant":1,"YearFrom":2019,"Category":"Normal","Theme":"Pick A Model","ThemeGroup":"LEGO Brand Store","Subtheme":null,"SetName":"Vampire Bat","Image":"X","ImageFilename":"VAMPIREBAT-1","USRetailPrice":null,"UKRetailPrice":null,"CARetailPrice":null,"DERetailPrice":null,"USDateAdded":null,"USDateRemoved":null,"Pieces":19,"Minifigs":null,"MinifigNumbers":null,"PackagingType":null,"Availability":null,"USItemNumber":null,"EUItemNumber":null,"EAN":null,"UPC":null,"Width":null,"Height":null,"Depth":null,"Weight":null,"ModelDimension1":null,"ModelDimension2":null,"ModelDimension3":null,"AgeMin":null,"AgeMax":null,"OwnCount":null,"WantCount":null,"InstructionsCount":null,"AdditionalImageCount":null,"Released":null,"Rating":null,"BrickLinkSoldPriceNew":null,"BrickLinkSoldPriceUsed":null,"Designers":null,"LaunchDate":null,"ExitDate":null,"link":"https://www.bricklink.com/v2/catalog/catalogitem.page?S=VAMPIREBAT-1#T=P","productImage":"https://cdn.rebrickable.com/media/sets/vampirebat-1.jpg","instructionsLink":"","type":"Set","New":null,"Used":null,"ExclusiveMinifigNumbers":null,"ExclusiveMinifigCount":null,"CurrentRRPBaseline":null},{"SetID":77410,"Number":"XMASTREE","Variant":1,"YearFrom":2019,"Category":"Normal","Theme":"Pick A Model","ThemeGroup":"LEGO Brand Store","Subtheme":null,"SetName":"Christmas Tree","Image":"X","ImageFilename":"XMASTREE-1","USRetailPrice":null,"UKRetailPrice":null,"CARetailPrice":null,"DERetailPrice":null,"USDateAdded":null,"USDateRemoved":null,"Pieces":26,"Minifigs":null,"MinifigNumbers":null,"PackagingType":null,"Availability":null,"USItemNumber":null,"EUItemNumber":null,"EAN":null,"UPC":null,"Width":null,"Height":null,"Depth":null,"Weight":null,"ModelDimension1":null,"ModelDimension2":null,"ModelDimension3":null,"AgeMin":null,"AgeMax":null,"OwnCount":null,"WantCount":null,"InstructionsCount":null,"AdditionalImageCount":null,"Released":null,"Rating":null,"BrickLinkSoldPriceNew":null,"BrickLinkSoldPriceUsed":null,"Designers":null,"LaunchDate":null,"ExitDate":null,"link":"https://www.bricklink.com/v2/catalog/catalogitem.page?S=XMASTREE-1#T=P","productImage":"https://cdn.rebrickable.com/media/sets/xmastree-1.jpg","instructionsLink":"","type":"Set","New":null,"Used":null,"ExclusiveMinifigNumbers":null,"ExclusiveMinifigCount":null,"CurrentRRPBaseline":null}]