[{"SetID":65923,"Number":6029152,"Variant":1,"YearFrom":2013,"Category":"Normal","Theme":"Series 11 Minifigures","ThemeGroup":"Collectible Minifigures","Subtheme":null,"SetName":"Series 11 - Sealed Box","Image":"X","ImageFilename":"6029152-1","USRetailPrice":null,"UKRetailPrice":null,"CARetailPrice":null,"DERetailPrice":null,"USDateAdded":null,"USDateRemoved":null,"Pieces":0,"Minifigs":null,"MinifigNumbers":null,"PackagingType":null,"Availability":null,"USItemNumber":null,"EUItemNumber":null,"EAN":null,"UPC":null,"Width":null,"Height":null,"Depth":null,"Weight":null,"ModelDimension1":null,"ModelDimension2":null,"ModelDimension3":null,"AgeMin":null,"AgeMax":null,"OwnCount":null,"WantCount":null,"InstructionsCount":null,"AdditionalImageCount":null,"Released":null,"Rating":null,"BrickLinkSoldPriceNew":null,"BrickLinkSoldPriceUsed":null,"Designers":null,"LaunchDate":null,"ExitDate":null,"link":"https://www.bricklink.com/v2/catalog/catalogitem.page?S=6029152-1#T=P","productImage":"https://cdn.rebrickable.com/media/sets/6029152-1.jpg","instructionsLink":"","type":"Set","New":null,"Used":null,"ExclusiveMinifigNumbers":null,"ExclusiveMinifigCount":null,"CurrentRRPBaseline":null},{"SetID":68504,"Number":71002,"Variant":15,"YearFrom":2013,"Category":"Normal","Theme":"Series 11 Minifigures","ThemeGroup":"Collectible Minifigures","Subtheme":null,"SetName":"Constable","Image":"X","ImageFilename":"71002-15","USRetailPrice":null,"UKRetailPrice":null,"CARetailPrice":null,"DERetailPrice":null,"USDateAdded":null,"USDateRemoved":null,"Pieces":6,"Minifigs":null,"MinifigNumbers":null,"PackagingType":null,"Availability":null,"USItemNumber":null,"EUItemNumber":null,"EAN":null,"UPC":null,"Width":null,"Height":null,"Depth":null,"Weight":null,"ModelDimension1":null,"ModelDimension2":null,"ModelDimension3":null,"AgeMin":null,"AgeMax":null,"OwnCount":null,"WantCount":null,"InstructionsCount":null,"AdditionalImageCount":null,"Released":null,"Rating":null,"BrickLinkSoldPriceNew":null,"BrickLinkSoldPriceUsed":null,"Designers":null,"LaunchDate":null,"ExitDate":null,"link":"https://www.bricklink.com/v2/catalog/catalogitem.page?S=71002-15#T=P","productImage":"https://cdn.rebrickable.com/media/sets/71002-15.jpg","instructionsLink":"","type":"Set","New":null,"Used":null,"ExclusiveMinifigNumbers":null,"ExclusiveMinifigCount":null,"CurrentRRPBaseline":null},{"SetID":68502,"Number":71002,"Variant":13,"YearFrom":2013,"Category":"Normal","Theme":"Series 11 Minifigures","ThemeGroup":"Collectible Minifigures","Subtheme":null,"SetName":"Diner Waitress","Image":"X","ImageFilename":"71002-13","USRetailPrice":null,"UKRetailPrice":null,"CARetailPrice":null,"DERetailPrice":null,"USDateAdded":null,"USDateRemoved":null,"Pieces":10,"Minifigs":null,"MinifigNumbers":null,"PackagingType":null,"Availability":null,"USItemNumber":null,"EUItemNumber":null,"EAN":null,"UPC":null,"Width":null,"Height":null,"Depth":null,"Weight":null,"ModelDimension1":null,"ModelDimension2":null,"ModelDimension3":null,"AgeMin":null,"AgeMax":null,"OwnCount":null,"WantCount":null,"InstructionsCount":null,"AdditionalImageCount":null,"Released":null,"Rating":null,"BrickLinkSoldPriceNew":null,"BrickLinkSoldPriceUsed":null,"Designers":null,"LaunchDate":null,"ExitDate":null,"link":"https://www.bricklink.com/v2/catalog/catalogitem.page?S=71002-13#T=P","productImage":"https://cdn.rebrickable.com/media/sets/71002-13.jpg","instructionsLink":"","type":"Set","New":null,"Used":null,"ExclusiveMinifigNumbers":null,"ExclusiveMinifigCount":null,"CurrentRRPBaseline":null},{"SetID":68509,"Number":71002,"Variant":4,"YearFrom":2013,"Category":"Normal","Theme":"Series 11 Minifigures","ThemeGroup":"Collectible Minifigures","Subtheme":null,"SetName":"Evil Mech","Image":"X","ImageFilename":"71002-4","USRetailPrice":null,"UKRetailPrice":null,"CARetailPrice":null,"DERetailPrice":null,"USDateAdded":null,"USDateRemoved":null,"Pieces":8,"Minifigs":null,"MinifigNumbers":null,"PackagingType":null,"Availability":null,"USItemNumber":null,"EUItemNumber":null,"EAN":null,"UPC":null,"Width":null,"Height":null,"Depth":null,"Weight":null,"ModelDimension1":null,"ModelDimension2":null,"ModelDimension3":null,"AgeMin":null,"AgeMax":null,"OwnCount":null,"WantCount":null,"InstructionsCount":null,"AdditionalImageCount":null,"Released":null,"Rating":null,"BrickLinkSoldPriceNew":null,"BrickLinkSoldPriceUsed":null,"Designers":null,"LaunchDate":null,"ExitDate":null,"link":"https://www.bricklink.com/v2/catalog/catalogitem.page?S=71002-4#T=P","productImage":"https://cdn.rebrickable.com/media/sets/71002-4.jpg","instructionsLink":"","type":"Set","New":null,"Used":null,"ExclusiveMinifigNumbers":null,"ExclusiveMinifigCount":null,"CurrentRRPBaseline":null},{"SetID":68511,"Number":71002,"Variant":6,"YearFrom":2013,"Category":"Normal","Theme":"Series 11 Minifigures","ThemeGroup":"Collectible Minifigures","Subtheme":null,"SetName":"Gingerbread Man","Image":"X","ImageFilename":"71002-6","USRetailPrice":null,"UKRetailPrice":null,"CARetailPrice":null,"DERetailPrice":null,"USDateAdded":null,"USDateRemoved":null,"Pieces":5,"Minifigs":null,"MinifigNumbers":null,"PackagingType":null,"Availability":null,"USItemNumber":null,"EUItemNumber":null,"EAN":null,"UPC":null,"Width":null,"Height":null,"Depth":null,"Weight":null,"ModelDimension1":null,"ModelDimension2":null,"ModelDimension3":null,"AgeMin":null,"AgeMax":null,"OwnCount":null,"WantCount":null,"InstructionsCount":null,"AdditionalImageCount":null,"Released":null,"Rating":null,"BrickLinkSoldPriceNew":null,"BrickLinkSoldPriceUsed":null,"Designers":null,"LaunchDate":null,"ExitDate":null,"link":"https://www.bricklink.com/v2/catalog/catalogitem.page?S=71002-6#T=P","productImage":"https://cdn.rebrickable.com/media/sets/71002-6.jpg","instructionsLink":"","type":"Set","New":null,"Used":null,"ExclusiveMinifigNumbers":null,"ExclusiveMinifigCount":null,"CurrentRRPBaseline":null},{"SetID":68503,"Number":71002,"Variant":14,"YearFrom":2013,"Category":"Normal","Theme":"Series 11 Minifigures","ThemeGroup":"Collectible Minifigures","Subtheme":null,"SetName":"Grandma","Image":"X","ImageFilename":"71002-14","USRetailPrice":null,"UKRetailPrice":null,"CARetailPrice":null,"DERetailPrice":null,"USDateAdded":null,"USDateRemoved":null,"Pieces":7,"Minifigs":null,"MinifigNumbers":null,"PackagingType":null,"Availability":null,"USItemNumber":null,"EUItemNumber":null,"EAN":null,"UPC":null,"Width":null,"Height":null,"Depth":null,"Weight":null,"ModelDimension1":null,"ModelDimension2":null,"ModelDimension3":null,"AgeMin":null,"AgeMax":null,"OwnCount":null,"WantCount":null,"InstructionsCount":null,"AdditionalImageCount":null,"Released":null,"Rating":null,"BrickLinkSoldPriceNew":null,"BrickLinkSoldPriceUsed":null,"Designers":null,"LaunchDate":null,"ExitDate":null,"link":"https://www.bricklink.com/v2/catalog/catalogitem.page?S=71002-14#T=P","productImage":"https://cdn.rebrickable.com/media/sets/71002-14.jpg","instructionsLink":"","type":"Set","New":null,"Used":null,"ExclusiveMinifigNumbers":null,"ExclusiveMinifigCount":null,"CurrentRRPBaseline":null},{"SetID":68512,"Number":71002,"Variant":7,"YearFrom":2013,"Category":"Normal","Theme":"Series 11 Minifigures","ThemeGroup":"Collectible Minifigures","Subtheme":null,"SetName":"Holiday Elf","Image":"X","ImageFilename":"71002-7","USRetailPrice":null,"UKRetailPrice":null,"CARetailPrice":null,"DERetailPrice":null,"USDateAdded":null,"USDateRemoved":null,"Pieces":8,"Minifigs":null,"MinifigNumbers":null,"PackagingType":null,"Availability":null,"USItemNumber":null,"EUItemNumber":null,"EAN":null,"UPC":null,"Width":null,"Height":null,"Depth":null,"Weight":null,"ModelDimension1":null,"ModelDimension2":null,"ModelDimension3":null,"AgeMin":null,"AgeMax":null,"OwnCount":null,"WantCount":null,"InstructionsCount":null,"AdditionalImageCount":null,"Released":null,"Rating":null,"BrickLinkSoldPriceNew":null,"BrickLinkSoldPriceUsed":null,"Designers":null,"LaunchDate":null,"ExitDate":null,"link":"https://www.bricklink.com/v2/catalog/catalogitem.page?S=71002-7#T=P","productImage":"https://cdn.rebrickable.com/media/sets/71002-7.jpg","instructionsLink":"","type":"Set","New":null,"Used":null,"ExclusiveMinifigNumbers":null,"ExclusiveMinifigCount":null,"CurrentRRPBaseline":null},{"SetID":68510,"Number":71002,"Variant":5,"YearFrom":2013,"Category":"Normal","Theme":"Series 11 Minifigures","ThemeGroup":"Collectible Minifigures","Subtheme":null,"SetName":"Island Warrior","Image":"X","ImageFilename":"71002-5","USRetailPrice":null,"UKRetailPrice":null,"CARetailPrice":null,"DERetailPrice":null,"USDateAdded":null,"USDateRemoved":null,"Pieces":8,"Minifigs":null,"MinifigNumbers":null,"PackagingType":null,"Availability":null,"USItemNumber":null,"EUItemNumber":null,"EAN":null,"UPC":null,"Width":null,"Height":null,"Depth":null,"Weight":null,"ModelDimension1":null,"ModelDimension2":null,"ModelDimension3":null,"AgeMin":null,"AgeMax":null,"OwnCount":null,"WantCount":null,"InstructionsCount":null,"AdditionalImageCount":null,"Released":null,"Rating":null,"BrickLinkSoldPriceNew":null,"BrickLinkSoldPriceUsed":null,"Designers":null,"LaunchDate":null,"ExitDate":null,"link":"https://www.bricklink.com/v2/catalog/catalogitem.page?S=71002-5#T=P","productImage":"https://cdn.rebrickable.com/media/sets/71002-5.jpg","instructionsLink":"","type":"Set","New":null,"Used":null,"ExclusiveMinifigNumbers":null,"ExclusiveMinifigCount":null,"CurrentRRPBaseline":null},{"SetID":68505,"Number":71002,"Variant":16,"YearFrom":2013,"Category":"Normal","Theme":"Series 11 Minifigures","ThemeGroup":"Collectible Minifigures","Subtheme":null,"SetName":"Lady Robot","Image":"X","ImageFilename":"71002-16","USRetailPrice":null,"UKRetailPrice":null,"CARetailPrice":null,"DERetailPrice":null,"USDateAdded":null,"USDateRemoved":null,"Pieces":6,"Minifigs":null,"MinifigNumbers":null,"PackagingType":null,"Availability":null,"USItemNumber":null,"EUItemNumber":null,"EAN":null,"UPC":null,"Width":null,"Height":null,"Depth":null,"Weight":null,"ModelDimension1":null,"ModelDimension2":null,"ModelDimension3":null,"AgeMin":null,"AgeMax":null,"OwnCount":null,"WantCount":null,"InstructionsCount":null,"AdditionalImageCount":null,"Released":null,"Rating":null,"BrickLinkSoldPriceNew":null,"BrickLinkSoldPriceUsed":null,"Designers":null,"LaunchDate":null,"ExitDate":null,"link":"https://www.bricklink.com/v2/catalog/catalogitem.page?S=71002-16#T=P","productImage":"https://cdn.rebrickable.com/media/sets/71002-16.jpg","instructionsLink":"","type":"Set","New":null,"Used":null,"ExclusiveMinifigNumbers":null,"ExclusiveMinifigCount":null,"CurrentRRPBaseline":null},{"SetID":68514,"Number":71002,"Variant":9,"YearFrom":2013,"Category":"Normal","Theme":"Series 11 Minifigures","ThemeGroup":"Collectible Minifigures","Subtheme":null,"SetName":"Mountain Climber","Image":"X","ImageFilename":"71002-9","USRetailPrice":null,"UKRetailPrice":null,"CARetailPrice":null,"DERetailPrice":null,"USDateAdded":null,"USDateRemoved":null,"Pieces":7,"Minifigs":null,"MinifigNumbers":null,"PackagingType":null,"Availability":null,"USItemNumber":null,"EUItemNumber":null,"EAN":null,"UPC":null,"Width":null,"Height":null,"Depth":null,"Weight":null,"ModelDimension1":null,"ModelDimension2":null,"ModelDimension3":null,"AgeMin":null,"AgeMax":null,"OwnCount":null,"WantCount":null,"InstructionsCount":null,"AdditionalImageCount":null,"Released":null,"Rating":null,"BrickLinkSoldPriceNew":null,"BrickLinkSoldPriceUsed":null,"Designers":null,"LaunchDate":null,"ExitDate":null,"link":"https://www.bricklink.com/v2/catalog/catalogitem.page?S=71002-9#T=P","productImage":"https://cdn.rebrickable.com/media/sets/71002-9.jpg","instructionsLink":"","type":"Set","New":null,"Used":null,"ExclusiveMinifigNumbers":null,"ExclusiveMinifigCount":null,"CurrentRRPBaseline":null},{"SetID":68508,"Number":71002,"Variant":3,"YearFrom":2013,"Category":"Normal","Theme":"Series 11 Minifigures","ThemeGroup":"Collectible Minifigures","Subtheme":null,"SetName":"Pretzel Girl","Image":"X","ImageFilename":"71002-3","USRetailPrice":null,"UKRetailPrice":null,"CARetailPrice":null,"DERetailPrice":null,"USDateAdded":null,"USDateRemoved":null,"Pieces":7,"Minifigs":null,"MinifigNumbers":null,"PackagingType":null,"Availability":null,"USItemNumber":null,"EUItemNumber":null,"EAN":null,"UPC":null,"Width":null,"Height":null,"Depth":null,"Weight":null,"ModelDimension1":null,"ModelDimension2":null,"ModelDimension3":null,"AgeMin":null,"AgeMax":null,"OwnCount":null,"WantCount":null,"InstructionsCount":null,"AdditionalImageCount":null,"Released":null,"Rating":null,"BrickLinkSoldPriceNew":null,"BrickLinkSoldPriceUsed":null,"Designers":null,"LaunchDate":null,"ExitDate":null,"link":"https://www.bricklink.com/v2/catalog/catalogitem.page?S=71002-3#T=P","productImage":"https://cdn.rebrickable.com/media/sets/71002-3.jpg","instructionsLink":"","type":"Set","New":null,"Used":null,"ExclusiveMinifigNumbers":null,"ExclusiveMinifigCount":null,"CurrentRRPBaseline":null},{"SetID":68501,"Number":71002,"Variant":12,"YearFrom":2013,"Category":"Normal","Theme":"Series 11 Minifigures","ThemeGroup":"Collectible Minifigures","Subtheme":null,"SetName":"Saxophone Player","Image":"X","ImageFilename":"71002-12","USRetailPrice":null,"UKRetailPrice":null,"CARetailPrice":null,"DERetailPrice":null,"USDateAdded":null,"USDateRemoved":null,"Pieces":6,"Minifigs":null,"MinifigNumbers":null,"PackagingType":null,"Availability":null,"USItemNumber":null,"EUItemNumber":null,"EAN":null,"UPC":null,"Width":null,"Height":null,"Depth":null,"Weight":null,"ModelDimension1":null,"ModelDimension2":null,"ModelDimension3":null,"AgeMin":null,"AgeMax":null,"OwnCount":null,"WantCount":null,"InstructionsCount":null,"AdditionalImageCount":null,"Released":null,"Rating":null,"BrickLinkSoldPriceNew":null,"BrickLinkSoldPriceUsed":null,"Designers":null,"LaunchDate":null,"ExitDate":null,"link":"https://www.bricklink.com/v2/catalog/catalogitem.page?S=71002-12#T=P","productImage":"https://cdn.rebrickable.com/media/sets/71002-12.jpg","instructionsLink":"","type":"Set","New":null,"Used":null,"ExclusiveMinifigNumbers":null,"ExclusiveMinifigCount":null,"CurrentRRPBaseline":null},{"SetID":68507,"Number":71002,"Variant":2,"YearFrom":2013,"Category":"Normal","Theme":"Series 11 Minifigures","ThemeGroup":"Collectible Minifigures","Subtheme":null,"SetName":"Scarecrow","Image":"X","ImageFilename":"71002-2","USRetailPrice":null,"UKRetailPrice":null,"CARetailPrice":null,"DERetailPrice":null,"USDateAdded":null,"USDateRemoved":null,"Pieces":7,"Minifigs":null,"MinifigNumbers":null,"PackagingType":null,"Availability":null,"USItemNumber":null,"EUItemNumber":null,"EAN":null,"UPC":null,"Width":null,"Height":null,"Depth":null,"Weight":null,"ModelDimension1":null,"ModelDimension2":null,"ModelDimension3":null,"AgeMin":null,"AgeMax":null,"OwnCount":null,"WantCount":null,"InstructionsCount":null,"AdditionalImageCount":null,"Released":null,"Rating":null,"BrickLinkSoldPriceNew":null,"BrickLinkSoldPriceUsed":null,"Designers":null,"LaunchDate":null,"ExitDate":null,"link":"https://www.bricklink.com/v2/catalog/catalogitem.page?S=71002-2#T=P","productImage":"https://cdn.rebrickable.com/media/sets/71002-2.jpg","instructionsLink":"","type":"Set","New":null,"Used":null,"ExclusiveMinifigNumbers":null,"ExclusiveMinifigCount":null,"CurrentRRPBaseline":null},{"SetID":68500,"Number":71002,"Variant":11,"YearFrom":2013,"Category":"Normal","Theme":"Series 11 Minifigures","ThemeGroup":"Collectible Minifigures","Subtheme":null,"SetName":"Scientist","Image":"X","ImageFilename":"71002-11","USRetailPrice":null,"UKRetailPrice":null,"CARetailPrice":null,"DERetailPrice":null,"USDateAdded":null,"USDateRemoved":null,"Pieces":7,"Minifigs":null,"MinifigNumbers":null,"PackagingType":null,"Availability":null,"USItemNumber":null,"EUItemNumber":null,"EAN":null,"UPC":null,"Width":null,"Height":null,"Depth":null,"Weight":null,"ModelDimension1":null,"ModelDimension2":null,"ModelDimension3":null,"AgeMin":null,"AgeMax":null,"OwnCount":null,"WantCount":null,"InstructionsCount":null,"AdditionalImageCount":null,"Released":null,"Rating":null,"BrickLinkSoldPriceNew":null,"BrickLinkSoldPriceUsed":null,"Designers":null,"LaunchDate":null,"ExitDate":null,"link":"https://www.bricklink.com/v2/catalog/catalogitem.page?S=71002-11#T=P","productImage":"https://cdn.rebrickable.com/media/sets/71002-11.jpg","instructionsLink":"","type":"Set","New":null,"Used":null,"ExclusiveMinifigNumbers":null,"ExclusiveMinifigCount":null,"CurrentRRPBaseline":null},{"SetID":68506,"Number":71002,"Variant":17,"YearFrom":2014,"Category":"Normal","Theme":"Series 11 Minifigures","ThemeGroup":"Collectible Minifigures","Subtheme":null,"SetName":"Series 11 - Complete - All Sets","Image":"X","ImageFilename":"71002-17","USRetailPrice":null,"UKRetailPrice":null,"CARetailPrice":null,"DERetailPrice":null,"USDateAdded":null,"USDateRemoved":null,"Pieces":0,"Minifigs":null,"MinifigNumbers":null,"PackagingType":null,"Availability":null,"USItemNumber":null,"EUItemNumber":null,"EAN":null,"UPC":null,"Width":null,"Height":null,"Depth":null,"Weight":null,"ModelDimension1":null,"ModelDimension2":null,"ModelDimension3":null,"AgeMin":null,"AgeMax":null,"OwnCount":null,"WantCount":null,"InstructionsCount":null,"AdditionalImageCount":null,"Released":null,"Rating":null,"BrickLinkSoldPriceNew":null,"BrickLinkSoldPriceUsed":null,"Designers":null,"LaunchDate":null,"ExitDate":null,"link":"https://www.bricklink.com/v2/catalog/catalogitem.page?S=71002-17#T=P","productImage":"https://cdn.rebrickable.com/media/sets/71002-17.jpg","instructionsLink":"","type":"Set","New":null,"Used":null,"ExclusiveMinifigNumbers":null,"ExclusiveMinifigCount":null,"CurrentRRPBaseline":null},{"SetID":68498,"Number":71002,"Variant":1,"YearFrom":2013,"Category":"Normal","Theme":"Series 11 Minifigures","ThemeGroup":"Collectible Minifigures","Subtheme":null,"SetName":"Series 11 - Random Bag","Image":"X","ImageFilename":"71002-1","USRetailPrice":null,"UKRetailPrice":null,"CARetailPrice":null,"DERetailPrice":null,"USDateAdded":null,"USDateRemoved":null,"Pieces":0,"Minifigs":null,"MinifigNumbers":null,"PackagingType":null,"Availability":null,"USItemNumber":null,"EUItemNumber":null,"EAN":null,"UPC":null,"Width":null,"Height":null,"Depth":null,"Weight":null,"ModelDimension1":null,"ModelDimension2":null,"ModelDimension3":null,"AgeMin":null,"AgeMax":null,"OwnCount":null,"WantCount":null,"InstructionsCount":null,"AdditionalImageCount":null,"Released":null,"Rating":null,"BrickLinkSoldPriceNew":null,"BrickLinkSoldPriceUsed":null,"Designers":null,"LaunchDate":null,"ExitDate":null,"link":"https://www.bricklink.com/v2/catalog/catalogitem.page?S=71002-1#T=P","productImage":"https://cdn.rebrickable.com/media/sets/71002-0.jpg","instructionsLink":"","type":"Set","New":null,"Used":null,"ExclusiveMinifigNumbers":null,"ExclusiveMinifigCount":null,"CurrentRRPBaseline":null},{"SetID":68499,"Number":71002,"Variant":10,"YearFrom":2013,"Category":"Normal","Theme":"Series 11 Minifigures","ThemeGroup":"Collectible Minifigures","Subtheme":null,"SetName":"Welder","Image":"X","ImageFilename":"71002-10","USRetailPrice":null,"UKRetailPrice":null,"CARetailPrice":null,"DERetailPrice":null,"USDateAdded":null,"USDateRemoved":null,"Pieces":7,"Minifigs":null,"MinifigNumbers":null,"PackagingType":null,"Availability":null,"USItemNumber":null,"EUItemNumber":null,"EAN":null,"UPC":null,"Width":null,"Height":null,"Depth":null,"Weight":null,"ModelDimension1":null,"ModelDimension2":null,"ModelDimension3":null,"AgeMin":null,"AgeMax":null,"OwnCount":null,"WantCount":null,"InstructionsCount":null,"AdditionalImageCount":null,"Released":null,"Rating":null,"BrickLinkSoldPriceNew":null,"BrickLinkSoldPriceUsed":null,"Designers":null,"LaunchDate":null,"ExitDate":null,"link":"https://www.bricklink.com/v2/catalog/catalogitem.page?S=71002-10#T=P","productImage":"https://cdn.rebrickable.com/media/sets/71002-10.jpg","instructionsLink":"","type":"Set","New":null,"Used":null,"ExclusiveMinifigNumbers":null,"ExclusiveMinifigCount":null,"CurrentRRPBaseline":null},{"SetID":68513,"Number":71002,"Variant":8,"YearFrom":2013,"Category":"Normal","Theme":"Series 11 Minifigures","ThemeGroup":"Collectible Minifigures","Subtheme":null,"SetName":"Yeti","Image":"X","ImageFilename":"71002-8","USRetailPrice":null,"UKRetailPrice":null,"CARetailPrice":null,"DERetailPrice":null,"USDateAdded":null,"USDateRemoved":null,"Pieces":5,"Minifigs":null,"MinifigNumbers":null,"PackagingType":null,"Availability":null,"USItemNumber":null,"EUItemNumber":null,"EAN":null,"UPC":null,"Width":null,"Height":null,"Depth":null,"Weight":null,"ModelDimension1":null,"ModelDimension2":null,"ModelDimension3":null,"AgeMin":null,"AgeMax":null,"OwnCount":null,"WantCount":null,"InstructionsCount":null,"AdditionalImageCount":null,"Released":null,"Rating":null,"BrickLinkSoldPriceNew":null,"BrickLinkSoldPriceUsed":null,"Designers":null,"LaunchDate":null,"ExitDate":null,"link":"https://www.bricklink.com/v2/catalog/catalogitem.page?S=71002-8#T=P","productImage":"https://cdn.rebrickable.com/media/sets/71002-8.jpg","instructionsLink":"","type":"Set","New":null,"Used":null,"ExclusiveMinifigNumbers":null,"ExclusiveMinifigCount":null,"CurrentRRPBaseline":null}]